Metadata-Version: 2.1
Name: distributions-mx-hsl
Version: 0.8
Summary: Gaussian & Binomial distributions
Home-page: UNKNOWN
Author: mx-hsl
License: UNKNOWN
Platform: UNKNOWN
Classifier: License :: OSI Approved :: MIT License
